jinja2_typogrify.py
setup.py
Jinja2_Typogrify.egg-info/PKG-INFO
Jinja2_Typogrify.egg-info/SOURCES.txt
Jinja2_Typogrify.egg-info/dependency_links.txt
Jinja2_Typogrify.egg-info/requires.txt
Jinja2_Typogrify.egg-info/top_level.txt