Metadata-Version: 1.0
Name: Jinja2-Typogrify
Version: 0.1.1
Summary: Jinja2-Typogrify
Home-page: https://github.com/raicheff/jinja2-typogrify
Author: Boris Raicheff
Author-email: b@raicheff.com
License: UNKNOWN
Platform: UNKNOWN
